haro/__init__.py
haro/api.py
haro/tests/__init__.py
haro/tests/test_api.py
haro-2018.11.15.dist-info/LICENSE
haro-2018.11.15.dist-info/METADATA
haro-2018.11.15.dist-info/WHEEL
haro-2018.11.15.dist-info/top_level.txt
haro-2018.11.15.dist-info/RECORD
