Metadata-Version: 2.1
Name: haro
Version: 2018.11.15
Summary: Haro.ai Python Library
Home-page: https://github.com/empiricalresults/haro-python-sdk
Author: Empirical Results Inc.
Author-email: info@haro.ai
License: Apache License Version 2.0, January 2004
Platform: UNKNOWN
Classifier: Programming Language :: Python :: 3.5
Classifier: Programming Language :: Python :: 2.7
Classifier: Intended Audience :: Developers
Classifier: Topic :: Scientific/Engineering :: Artificial Intelligence
Requires-Dist: six (>=1.11.0)
Requires-Dist: requests (>=2.18.4)
